audio_recorder_streamlit/__init__.py
audio_recorder_streamlit/example.py
audio_recorder_streamlit/frontend/.env
audio_recorder_streamlit/frontend/.prettierrc
audio_recorder_streamlit/frontend/package-lock.json
audio_recorder_streamlit/frontend/package.json
audio_recorder_streamlit/frontend/tsconfig.json
audio_recorder_streamlit/frontend/build/asset-manifest.json
audio_recorder_streamlit/frontend/build/bootstrap.min.css
audio_recorder_streamlit/frontend/build/index.html
audio_recorder_streamlit/frontend/build/precache-manifest.833dd8e76b98195d8f48f20229ebdf7c.js
audio_recorder_streamlit/frontend/build/service-worker.js
audio_recorder_streamlit/frontend/build/static/js/2.149c4397.chunk.js
audio_recorder_streamlit/frontend/build/static/js/2.149c4397.chunk.js.LICENSE.txt
audio_recorder_streamlit/frontend/build/static/js/2.149c4397.chunk.js.map
audio_recorder_streamlit/frontend/build/static/js/main.4b1f4dd5.chunk.js
audio_recorder_streamlit/frontend/build/static/js/main.4b1f4dd5.chunk.js.LICENSE.txt
audio_recorder_streamlit/frontend/build/static/js/main.4b1f4dd5.chunk.js.map
audio_recorder_streamlit/frontend/build/static/js/main.f2490ba5.js
audio_recorder_streamlit/frontend/build/static/js/main.f2490ba5.js.LICENSE.txt
audio_recorder_streamlit/frontend/build/static/js/main.f2490ba5.js.map
audio_recorder_streamlit/frontend/build/static/js/main.ff59c8ed.js
audio_recorder_streamlit/frontend/build/static/js/main.ff59c8ed.js.LICENSE.txt
audio_recorder_streamlit/frontend/build/static/js/main.ff59c8ed.js.map
audio_recorder_streamlit/frontend/build/static/js/runtime-main.44d30fc2.js
audio_recorder_streamlit/frontend/build/static/js/runtime-main.44d30fc2.js.map
audio_recorder_streamlit/frontend/public/bootstrap.min.css
audio_recorder_streamlit/frontend/public/index.html
audio_recorder_streamlit/frontend/src/AudioRecorder.tsx
audio_recorder_streamlit/frontend/src/index.tsx
audio_recorder_streamlit/frontend/src/react-app-env.d.ts
audio_recorder_streamlit-0.0.10.dist-info/LICENSE
audio_recorder_streamlit-0.0.10.dist-info/METADATA
audio_recorder_streamlit-0.0.10.dist-info/WHEEL
audio_recorder_streamlit-0.0.10.dist-info/top_level.txt
audio_recorder_streamlit-0.0.10.dist-info/RECORD
