Metadata-Version: 2.1
Name: audio-recorder-streamlit
Version: 0.0.10
Author-email: Johan Leduc <johan.leduc90@gmail.com>
License: Copyright (c) 2018-2021 Streamlit Inc.
Project-URL: Source, https://github.com/Joooohan/audio-recorder-streamlit
Keywords: streamlit,audio,input
Classifier: Programming Language :: Python
Requires-Python: >=3.8
License-File: LICENSE
Requires-Dist: streamlit>=1.12.0
Requires-Dist: altair<5
